nomenclature/__init__.py
nomenclature/cli.py
nomenclature/code.py
nomenclature/codelist.py
nomenclature/config.py
nomenclature/core.py
nomenclature/countries.py
nomenclature/definition.py
nomenclature/exceptions.py
nomenclature/logging.yaml
nomenclature/nuts.py
nomenclature/processor/__init__.py
nomenclature/processor/aggregator.py
nomenclature/processor/data_validator.py
nomenclature/processor/iamc.py
nomenclature/processor/meta.py
nomenclature/processor/processor.py
nomenclature/processor/region.py
nomenclature/processor/required_data.py
nomenclature/py.typed
nomenclature/testing.py
nomenclature/utils.py
nomenclature_iamc-0.28.1.dist-info/METADATA
nomenclature_iamc-0.28.1.dist-info/WHEEL
nomenclature_iamc-0.28.1.dist-info/entry_points.txt
nomenclature_iamc-0.28.1.dist-info/licenses/LICENSE
nomenclature_iamc-0.28.1.dist-info/RECORD
