Metadata-Version: 2.4
Name: nomenclature-iamc
Version: 0.28.1
Summary: Package for managing codelists & attributes for IAMC-format datasets
License-Expression: Apache-2.0
License-File: LICENSE
Author: Scenario Services team, ECE program, IIASA
Requires-Python: >=3.11,<3.14
Classifier: Programming Language :: Python :: 3
Classifier: Programming Language :: Python :: 3.11
Classifier: Programming Language :: Python :: 3.12
Classifier: Programming Language :: Python :: 3.13
Requires-Dist: PyYAML (>=6.0.1,<7.0)
Requires-Dist: click (>=8,<8.2)
Requires-Dist: gitpython (>=3.1.40,<4.0)
Requires-Dist: numpy (>=1.23.0,<3.0)
Requires-Dist: openpyxl (>=3.1.2,<4.0)
Requires-Dist: pandas (>=1.5.2,<3.0)
Requires-Dist: pyam-iamc (>=3.1,<4.0)
Requires-Dist: pycountry (==23.12.11)
Requires-Dist: pydantic (>=2,<3)
Requires-Dist: pysquirrel (>=1.1,<2.0)
Requires-Dist: scse-toolkit (>=0.14.0,<0.16.0)
